bilby_lisa/__init__.py
bilby_lisa/_version.py
bilby_lisa/bilby_pipe.py
bilby_lisa/interferometer.py
bilby_lisa/networks.py
bilby_lisa/parallel_bilby.py
bilby_lisa/parser.py
bilby_lisa/source.py
bilby_lisa/utils.py
bilby_lisa-1.0.0a3.dist-info/METADATA
bilby_lisa-1.0.0a3.dist-info/WHEEL
bilby_lisa-1.0.0a3.dist-info/entry_points.txt
bilby_lisa-1.0.0a3.dist-info/top_level.txt
bilby_lisa-1.0.0a3.dist-info/RECORD
