Metadata-Version: 2.1
Name: bilby_lisa
Version: 1.0.0a3
Summary: Python package to extend the functionality of `bilby` to perform Bayesian inference with the LISA gravitational-wave detector
Author-email: Charlie Hoy <charlie.hoy@port.ac.uk>, Laura Nuttall <laura.nuttall@port.ac.uk>
License: MIT
Classifier: License :: OSI Approved :: MIT License
Classifier: Natural Language :: English
Classifier: Programming Language :: Python
Classifier: Programming Language :: Python :: 3
Classifier: Programming Language :: Python :: 3.9
Classifier: Programming Language :: Python :: 3.10
Requires-Python: >=3.9
Requires-Dist: bilby
Requires-Dist: bilby-pipe
Provides-Extra: docs
Requires-Dist: Sphinx >=1.2.2 ; extra == 'docs'
Requires-Dist: sphinx-immaterial ; extra == 'docs'
Requires-Dist: sphinx-tabs ; extra == 'docs'
Provides-Extra: parallel
Requires-Dist: parallel-bilby ; extra == 'parallel'
